stage_tracker/__init__.py
stage_tracker/tracker.py
stage_tracker-0.1.1.dist-info/licenses/LICENSE
stage_tracker-0.1.1.dist-info/METADATA
stage_tracker-0.1.1.dist-info/WHEEL
stage_tracker-0.1.1.dist-info/top_level.txt
stage_tracker-0.1.1.dist-info/RECORD
