Metadata-Version: 2.4
Name: stage-tracker
Version: 0.1.1
Summary: Lightweight complete run and individual stage tracker for modularized pipelines
Author-email: Karim Ahmed <karim.ahmed4815@gmail.com>
License: MIT
Requires-Python: >=3.8
License-File: LICENSE
Dynamic: license-file
